AUTHORS.rst
HISTORY.rst
LICENSE.rst
MANIFEST.in
README.rst
requirements-dev.txt
requirements-release.txt
requirements.txt
setup.cfg
setup.py
django_url_filter_fix.egg-info/PKG-INFO
django_url_filter_fix.egg-info/SOURCES.txt
django_url_filter_fix.egg-info/dependency_links.txt
django_url_filter_fix.egg-info/requires.txt
django_url_filter_fix.egg-info/top_level.txt
docs/Makefile
docs/big_picture.rst
docs/conf.py
docs/history.rst
docs/index.rst
docs/usage.rst
docs/api/modules.rst
docs/api/url_filter.backends.base.rst
docs/api/url_filter.backends.django.rst
docs/api/url_filter.backends.plain.rst
docs/api/url_filter.backends.rst
docs/api/url_filter.backends.sqlalchemy.rst
docs/api/url_filter.exceptions.rst
docs/api/url_filter.fields.rst
docs/api/url_filter.filters.rst
docs/api/url_filter.filtersets.base.rst
docs/api/url_filter.filtersets.django.rst
docs/api/url_filter.filtersets.plain.rst
docs/api/url_filter.filtersets.rst
docs/api/url_filter.filtersets.sqlalchemy.rst
docs/api/url_filter.integrations.drf.rst
docs/api/url_filter.integrations.drf_coreapi.rst
docs/api/url_filter.integrations.rst
docs/api/url_filter.rst
docs/api/url_filter.utils.rst
docs/api/url_filter.validators.rst
url_filter/__init__.py
url_filter/constants.py
url_filter/exceptions.py
url_filter/fields.py
url_filter/filters.py
url_filter/utils.py
url_filter/validators.py
url_filter/backends/__init__.py
url_filter/backends/base.py
url_filter/backends/django.py
url_filter/backends/plain.py
url_filter/backends/sqlalchemy.py
url_filter/filtersets/__init__.py
url_filter/filtersets/base.py
url_filter/filtersets/django.py
url_filter/filtersets/plain.py
url_filter/filtersets/sqlalchemy.py
url_filter/integrations/__init__.py
url_filter/integrations/drf.py
url_filter/integrations/drf_coreapi.py